[
  { 
    "descricao": "Eliminatórias da Copa do Mundo FIFA de 2022",
    "local": {
      "nome": "Maracanã",
      "imagem": "TODO"
    },
    "mandante": {
      "nome": "Brasil",
      "estrelas": 5,
      "imagem": "https://www.bandeirasnacionais.com/data/flags/normal/br.png"
    },
    "visitante": {
      "nome": "Argentina",
      "estrelas": 5,
      "imagem": "https://www.bandeirasnacionais.com/data/flags/normal/ar.png"
    }
  }, 
    { 
    "descricao": "Eliminatórias da Copa do Mundo FIFA de 2022",
    "local": {
      "nome": "Centenario",
      "imagem": "TODO"
    },
    "mandante": {
      "nome": "Uruguai",
      "estrelas": 4,
      "imagem": "https://www.bandeirasnacionais.com/data/flags/normal/uy.png"
    },
    "visitante": {
      "nome": "México",
      "estrelas": 3,
      "imagem": "https://www.bandeirasnacionais.com/data/flags/normal/mx.png"
    }
  },
    }, 
    { 
    "descricao": "Eliminatórias da Copa do Mundo FIFA de 2022",
    "local": {
      "nome": "Nacional Julio Martínez Prádanos",
      "imagem": "TODO"
    },
    "mandante": {
      "nome": "Chile",
      "estrelas": 4,
      "imagem": "https://www.bandeirasnacionais.com/data/flags/normal/cl.png"
    },
    "visitante": {
      "nome": "Peru",
      "estrelas": 3,
      "imagem": "https://www.bandeirasnacionais.com/data/flags/normal/pe.png"
    }
  }
]
